{
  "main": {
    "id": "d8a22c8088368c8e",
    "type": "split",
    "children": [
      {
        "id": "1d2d83c4fb7b4a61",
        "type": "tabs",
        "children": [
          {
            "id": "7945a1591a48e86e",
            "type": "leaf",
            "state": {
              "type": "markdown",
              "state": {
                "file": "Agregasi dengan GROUP BY & HAVING.md",
                "mode": "source",
                "source": false
              }
            }
          }
        ]
      }
    ],
    "direction": "vertical"
  },
  "left": {
    "id": "4dcdda2b7bab824c",
    "type": "split",
    "children": [
      {
        "id": "d74403679fe46787",
        "type": "tabs",
        "children": [
          {
            "id": "244778ff4f385ad4",
            "type": "leaf",
            "state": {
              "type": "file-explorer",
              "state": {
                "sortOrder": "alphabetical"
              }
            }
          },
          {
            "id": "0816c14ad40586b3",
            "type": "leaf",
            "state": {
              "type": "search",
              "state": {
                "query": "",
                "matchingCase": false,
                "explainSearch": false,
                "collapseAll": false,
                "extraContext": false,
                "sortOrder": "alphabetical"
              }
            }
          },
          {
            "id": "49f10721d34c065f",
            "type": "leaf",
            "state": {
              "type": "bookmarks",
              "state": {}
            }
          }
        ]
      }
    ],
    "direction": "horizontal",
    "width": 300
  },
  "right": {
    "id": "f52d643286fa3dfa",
    "type": "split",
    "children": [
      {
        "id": "e7380d8f52ce7abc",
        "type": "tabs",
        "children": [
          {
            "id": "fbfce909675811c1",
            "type": "leaf",
            "state": {
              "type": "backlink",
              "state": {
                "file": "Agregasi dengan GROUP BY & HAVING.md",
                "collapseAll": false,
                "extraContext": false,
                "sortOrder": "alphabetical",
                "showSearch": false,
                "searchQuery": "",
                "backlinkCollapsed": false,
                "unlinkedCollapsed": true
              }
            }
          },
          {
            "id": "cc3736abd121a85e",
            "type": "leaf",
            "state": {
              "type": "outgoing-link",
              "state": {
                "file": "Agregasi dengan GROUP BY & HAVING.md",
                "linksCollapsed": false,
                "unlinkedCollapsed": true
              }
            }
          },
          {
            "id": "c744781ecc8f0b5b",
            "type": "leaf",
            "state": {
              "type": "tag",
              "state": {
                "sortOrder": "frequency",
                "useHierarchy": true
              }
            }
          },
          {
            "id": "9f84ec24888f83ad",
            "type": "leaf",
            "state": {
              "type": "outline",
              "state": {
                "file": "Agregasi dengan GROUP BY & HAVING.md"
              }
            }
          }
        ]
      }
    ],
    "direction": "horizontal",
    "width": 300,
    "collapsed": true
  },
  "left-ribbon": {
    "hiddenItems": {
      "switcher:Open quick switcher": false,
      "graph:Open graph view": false,
      "canvas:Create new canvas": false,
      "daily-notes:Open today's daily note": false,
      "templates:Insert template": false,
      "command-palette:Open command palette": false
    }
  },
  "active": "7945a1591a48e86e",
  "lastOpenFiles": []
}